oneNeuron/__init__.py
oneNeuron/perceptron.py
perceptron_pkg_abhaykeni-0.0.2.dist-info/METADATA
perceptron_pkg_abhaykeni-0.0.2.dist-info/WHEEL
perceptron_pkg_abhaykeni-0.0.2.dist-info/top_level.txt
perceptron_pkg_abhaykeni-0.0.2.dist-info/RECORD
