Metadata-Version: 2.1
Name: perceptron-pkg-abhaykeni
Version: 0.0.2
Summary: A small package for perceptron
Home-page: https://github.com/abhaykeni/perceptron-pkg
Author: abhaykeni
Author-email: abhaykeni@gmail.com
Project-URL: Bug Tracker, https://github.com/abhaykeni/perceptron-pkg/issues
Classifier: Programming Language :: Python :: 3
Classifier: License :: OSI Approved :: MIT License
Classifier: Operating System :: OS Independent
Requires-Python: >=3.6
Requires-Dist: numpy (==1.21.4)
Requires-Dist: pandas (==1.3.4)
Requires-Dist: joblib (==1.1.0)
